__init__.py
geogetter/__init__.py
geogetter-0.2.1.dist-info/LICENSE
geogetter-0.2.1.dist-info/METADATA
geogetter-0.2.1.dist-info/WHEEL
geogetter-0.2.1.dist-info/top_level.txt
geogetter-0.2.1.dist-info/RECORD
