Metadata-Version: 2.1
Name: geogetter
Version: 0.2.1
Summary: Very simple and lightweight geocoder
Author-email: Mikolaj Szczesny <miszczes0@gmail.com>
License-File: LICENSE
Requires-Dist: requests ==2.31.0
Provides-Extra: dev
Requires-Dist: black ; extra == 'dev'
